devantech_relays/__init__.py
devantech_relays/eth.py
devantech_relays-0.1.3.dist-info/WHEEL
devantech_relays-0.1.3.dist-info/METADATA
devantech_relays-0.1.3.dist-info/RECORD
