Metadata-Version: 2.1
Name: devantech-relays
Version: 0.1.3
Summary: Tool for controlling Devantech's ETH-series of relays
Author: Karl Fredrik Haugland
Author-email: kfh@tla.wtf
Requires-Python: >=3,<4
Classifier: Programming Language :: Python :: 3
Classifier: Programming Language :: Python :: 3.10
Classifier: Programming Language :: Python :: 3.4
Classifier: Programming Language :: Python :: 3.5
Classifier: Programming Language :: Python :: 3.6
Classifier: Programming Language :: Python :: 3.7
Classifier: Programming Language :: Python :: 3.8
Classifier: Programming Language :: Python :: 3.9
